aws_message/VERSION
aws_message/__init__.py
aws_message/crypto.py
aws_message/gather.py
aws_message/message.py
aws_message/mock_sqs.py
aws_message/processor.py
aws_message/sqs.py
aws_message/test.py
aws_message/tests/__init__.py
aws_message/tests/test_message.py
aws_message/tests/test_processor.py
aws_message/tests/test_sqs.py
aws_message_client-1.6.1.dist-info/licenses/LICENSE
aws_message_client-1.6.1.dist-info/METADATA
aws_message_client-1.6.1.dist-info/WHEEL
aws_message_client-1.6.1.dist-info/top_level.txt
aws_message_client-1.6.1.dist-info/RECORD
