Metadata-Version: 2.4
Name: aws-message-client
Version: 1.6.1
Summary: An application on which to build AWS SQS endpoints and SQS gatherers
Home-page: https://github.com/uw-it-aca/aws-message-client
Author: UW-IT SETS
Author-email: aca-it@uw.edu
License: Apache License, Version 2.0
Classifier: Environment :: Web Environment
Classifier: Intended Audience :: Developers
Classifier: License :: OSI Approved :: Apache Software License
Classifier: Operating System :: OS Independent
Classifier: Programming Language :: Python
License-File: LICENSE
Requires-Dist: boto3
Requires-Dist: cryptography
Requires-Dist: urllib3
Requires-Dist: commonconf
Requires-Dist: uw-memcached-clients
Dynamic: author
Dynamic: author-email
Dynamic: classifier
Dynamic: description
Dynamic: home-page
Dynamic: license
Dynamic: license-file
Dynamic: requires-dist
Dynamic: summary
